connectivity_agent.py
connectivity_agent-0.1.3.dist-info/METADATA
connectivity_agent-0.1.3.dist-info/WHEEL
connectivity_agent-0.1.3.dist-info/entry_points.txt
connectivity_agent-0.1.3.dist-info/licenses/LICENSE
connectivity_agent-0.1.3.dist-info/RECORD
