Metadata-Version: 2.4
Name: connectivity-agent
Version: 0.1.3
Summary: An AI agent that diagnoses network connectivity issues using OpenAI's Responses API
Project-URL: Homepage, https://github.com/brocla/connectivity_agent
Project-URL: Repository, https://github.com/brocla/connectivity_agent
Project-URL: Issues, https://github.com/brocla/connectivity_agent/issues
Author-email: Kevin Brown <connectivity_agent@whidit.com>
License: MIT
License-File: LICENSE
Keywords: agent,ai,diagnostics,networking,openai
Classifier: Development Status :: 3 - Alpha
Classifier: Intended Audience :: Developers
Classifier: License :: OSI Approved :: MIT License
Classifier: Programming Language :: Python :: 3
Classifier: Programming Language :: Python :: 3.10
Classifier: Programming Language :: Python :: 3.11
Classifier: Programming Language :: Python :: 3.12
Classifier: Topic :: System :: Networking
Requires-Python: >=3.10
Requires-Dist: openai>=2.8.0
